sir_bot_a_lot-0.2.0.dist-info/DESCRIPTION.rst
sir_bot_a_lot-0.2.0.dist-info/METADATA
sir_bot_a_lot-0.2.0.dist-info/RECORD
sir_bot_a_lot-0.2.0.dist-info/WHEEL
sir_bot_a_lot-0.2.0.dist-info/entry_points.txt
sir_bot_a_lot-0.2.0.dist-info/metadata.json
sir_bot_a_lot-0.2.0.dist-info/top_level.txt
sirbot/__init__.py
sirbot/cli/__init__.py
sirbot/cli/cli.py
sirbot/cli/config.py
sirbot/cli/initialize.py
sirbot/cli/plugin.py.mako
sirbot/cli/sirbot.yml.mako
sirbot/core/__init__.py
sirbot/core/__meta__.py
sirbot/core/config.yml
sirbot/core/core.py
sirbot/core/errors.py
sirbot/core/hookimpl.py
sirbot/core/hookspecs.py
sirbot/core/plugin.py
sirbot/registry/__init__.py
sirbot/utils/__init__.py
