Metadata-Version: 2.0
Name: sir-bot-a-lot
Version: 0.2.0
Summary: The good Sir Bot-a-lot. An asynchronous python bot framework.
Home-page: https://github.com/pyslackers/sir-bot-a-lot
Author: pythondev slack community
Author-email: pythondev.slack@gmail.com
License: MIT
Keywords: sirbot,chatbot,bot,slack
Platform: UNKNOWN
Classifier: Development Status :: 2 - Pre-Alpha
Classifier: Intended Audience :: Developers
Classifier: Topic :: Software Development
Classifier: License :: OSI Approved :: MIT License
Classifier: Natural Language :: English
Classifier: Programming Language :: Python :: 3
Classifier: Programming Language :: Python :: 3.5
Classifier: Programming Language :: Python :: 3.6
Classifier: Environment :: Console
Requires-Python: ~=3.5
Requires-Dist: aiohttp (==2.2.3)
Requires-Dist: async-timeout (==1.2.1)
Requires-Dist: chardet (==3.0.4)
Requires-Dist: mako (==1.0.6)
Requires-Dist: markupsafe (==1.0)
Requires-Dist: multidict (==3.1.0)
Requires-Dist: pluggy (==0.4.0)
Requires-Dist: pyyaml (==3.12)
Requires-Dist: yarl (==0.11.0)
Provides-Extra: dev
Requires-Dist: aiohttp (==2.2.3); extra == 'dev'
Requires-Dist: alabaster (==0.7.10); extra == 'dev'
Requires-Dist: async-timeout (==1.2.1); extra == 'dev'
Requires-Dist: babel (==2.4.0); extra == 'dev'
Requires-Dist: certifi (==2017.4.17); extra == 'dev'
Requires-Dist: chardet (==3.0.4); extra == 'dev'
Requires-Dist: click (==6.7); extra == 'dev'
Requires-Dist: commonmark (==0.5.4); extra == 'dev'
Requires-Dist: coverage (==4.4.1); extra == 'dev'
Requires-Dist: docutils (==0.13.1); extra == 'dev'
Requires-Dist: first (==2.0.1); extra == 'dev'
Requires-Dist: flake8 (==3.3.0); extra == 'dev'
Requires-Dist: idna (==2.5); extra == 'dev'
Requires-Dist: imagesize (==0.7.1); extra == 'dev'
Requires-Dist: jinja2 (==2.9.6); extra == 'dev'
Requires-Dist: markupsafe (==1.0); extra == 'dev'
Requires-Dist: mccabe (==0.6.1); extra == 'dev'
Requires-Dist: multidict (==3.1.0); extra == 'dev'
Requires-Dist: pip-tools (==1.9.0); extra == 'dev'
Requires-Dist: pluggy (==0.4.0); extra == 'dev'
Requires-Dist: pockets (==0.5.1); extra == 'dev'
Requires-Dist: py (==1.4.34); extra == 'dev'
Requires-Dist: pycodestyle (==2.3.1); extra == 'dev'
Requires-Dist: pyflakes (==1.5.0); extra == 'dev'
Requires-Dist: pygments (==2.2.0); extra == 'dev'
Requires-Dist: pytest (==3.1.3); extra == 'dev'
Requires-Dist: pytest-aiohttp (==0.1.3); extra == 'dev'
Requires-Dist: pytest-asyncio (==0.6.0); extra == 'dev'
Requires-Dist: pytest-cov (==2.5.1); extra == 'dev'
Requires-Dist: pytest-runner (==2.11.1); extra == 'dev'
Requires-Dist: pytz (==2017.2); extra == 'dev'
Requires-Dist: recommonmark (==0.4.0); extra == 'dev'
Requires-Dist: requests (==2.18.1); extra == 'dev'
Requires-Dist: six (==1.10.0); extra == 'dev'
Requires-Dist: snowballstemmer (==1.2.1); extra == 'dev'
Requires-Dist: sphinx (==1.6.3); extra == 'dev'
Requires-Dist: sphinx-pypi-upload (==0.2.1); extra == 'dev'
Requires-Dist: sphinxcontrib-asyncio (==0.2.0); extra == 'dev'
Requires-Dist: sphinxcontrib-napoleon (==0.6.1); extra == 'dev'
Requires-Dist: sphinxcontrib-websupport (==1.0.1); extra == 'dev'
Requires-Dist: tox (==2.7.0); extra == 'dev'
Requires-Dist: urllib3 (==1.21.1); extra == 'dev'
Requires-Dist: virtualenv (==15.1.0); extra == 'dev'
Requires-Dist: yarl (==0.11.0); extra == 'dev'
